yandex_maps/__init__.py
yandex_maps/exceptions.py
yandex_maps/yandex_maps.py
Yandexmaps-0.3.dist-info/LICENSE
Yandexmaps-0.3.dist-info/METADATA
Yandexmaps-0.3.dist-info/WHEEL
Yandexmaps-0.3.dist-info/top_level.txt
Yandexmaps-0.3.dist-info/RECORD
