Metadata-Version: 2.1
Name: Yandexmaps
Version: 0.3
Summary: Documentation > https://github.com/begyy/Yandexmaps
Home-page: https://github.com/begyy/Yandexmaps
Author: Sadullyev Behzod
Author-email: begymrx@gmail.com
License: UNKNOWN
Platform: UNKNOWN
Classifier: Programming Language :: Python :: 3
Classifier: License :: OSI Approved :: MIT License
Classifier: Operating System :: OS Independent
